setup.py
user_profile/__init__.py
user_profile/forms.py
user_profile/models.py
user_profile/tests.py
user_profile/urls.py
user_profile/views.py
user_profile.egg-info/PKG-INFO
user_profile.egg-info/SOURCES.txt
user_profile.egg-info/dependency_links.txt
user_profile.egg-info/not-zip-safe
user_profile.egg-info/top_level.txt