Metadata-Version: 1.0
Name: user-profile
Version: 1.0.0
Summary: user profile for pinterest apllication like in Django
Home-page: http://www.wisgoon.com/
Author: vahid chakoshy
Author-email: vchakoshy@gmail.com
License: UNKNOWN
Platform: UNKNOWN
